LPDT/__init__.py
LPDT/_criterion.py
LPDT/_estimator.py
LPDT/_splitter.py
LPDT/_tree.py
LPDT/tree.py
tests/__init__.py
tests/test_tree.py
tests/test_tree_cv.py
LPDT-0.0.2.dist-info/LICENSE
LPDT-0.0.2.dist-info/METADATA
LPDT-0.0.2.dist-info/WHEEL
LPDT-0.0.2.dist-info/top_level.txt
LPDT-0.0.2.dist-info/RECORD
