Metadata-Version: 2.1
Name: LPDT
Version: 0.0.2
Summary: Locally differentially Private Decision Tree
Home-page: https://github.com/Karlmyh/LPDT
Author: Yuheng Ma, Han Zhang
Author-email: yma@ruc.edu.cn
Classifier: Programming Language :: Python :: 3
Classifier: License :: OSI Approved :: MIT License
Requires-Python: >=3
License-File: LICENSE
Requires-Dist: numpy >=1.24.2
Requires-Dist: scikit-learn >=1.3.1
Requires-Dist: numba >=0.58.0
Requires-Dist: scipy >=1.11.2
